I2S_Transmitter.v
module I2S_Transmitter(
  input         clock,
  input         reset,
  input  [31:0] io_Tx,
  output        io_Ready,
  output        io_LRCLK,
  output        io_BCLK,
  output        io_MCLK,
  output [31:0] io_DATA,
  output        io_bDATA,
  output [1:0]  io_State_o,
  output [7:0]  io_BitCntr,
  output        io_tick,
  input  [15:0] io_sw,
  output [15:0] io_CLKR
);
`ifdef RANDOMIZE_REG_INIT
  reg [31:0] _RAND_0;
  reg [31:0] _RAND_1;
  reg [31:0] _RAND_2;
  reg [31:0] _RAND_3;
  reg [31:0] _RAND_4;
  reg [31:0] _RAND_5;
  reg [31:0] _RAND_6;
  reg [31:0] _RAND_7;
  reg [31:0] _RAND_8;
`endif // RANDOMIZE_REG_INIT
  reg  current_state; // @[Hello.scala 31:30]
  reg [7:0] Bit_Counter; // @[Hello.scala 32:30]
  reg [7:0] ClkCntr; // @[Hello.scala 33:30]
  reg  Tckr; // @[Hello.scala 34:30]
  reg  BCLKTckr; // @[Hello.scala 35:30]
  reg  LRClkr; // @[Hello.scala 36:30]
  reg  MCLKTckr; // @[Hello.scala 37:30]
  reg  bDATA; // @[Hello.scala 38:30]
  reg [31:0] DATA; // @[Hello.scala 39:30]
  wire [7:0] _ClkCntr_T_1 = ClkCntr + 8'h1; // @[Hello.scala 47:22]
  wire  _T_1 = ClkCntr == 8'h8; // @[Hello.scala 51:17]
  wire  _T_2 = ClkCntr == 8'h4 | _T_1; // @[Hello.scala 50:27]
  wire  _T_3 = ClkCntr == 8'hc; // @[Hello.scala 52:17]
  wire  _T_4 = _T_2 | _T_3; // @[Hello.scala 51:27]
  wire  _T_5 = ClkCntr == 8'h10; // @[Hello.scala 53:17]
  wire  _T_6 = _T_4 | _T_5; // @[Hello.scala 52:27]
  wire  _T_7 = ClkCntr == 8'h14; // @[Hello.scala 54:17]
  wire  _T_8 = _T_6 | _T_7; // @[Hello.scala 53:27]
  wire  _T_9 = ClkCntr == 8'h18; // @[Hello.scala 55:17]
  wire  _T_10 = _T_8 | _T_9; // @[Hello.scala 54:27]
  wire  _T_11 = ClkCntr == 8'h1c; // @[Hello.scala 56:17]
  wire  _T_12 = _T_10 | _T_11; // @[Hello.scala 55:27]
  wire  _T_13 = ClkCntr == 8'h20; // @[Hello.scala 57:17]
  wire  _T_14 = _T_12 | _T_13; // @[Hello.scala 56:27]
  wire  _T_15 = ClkCntr == 8'h24; // @[Hello.scala 58:17]
  wire  _T_16 = _T_14 | _T_15; // @[Hello.scala 57:27]
  wire  _T_17 = ClkCntr == 8'h28; // @[Hello.scala 59:17]
  wire  _T_18 = _T_16 | _T_17; // @[Hello.scala 58:27]
  wire  _T_19 = ClkCntr == 8'h2c; // @[Hello.scala 60:17]
  wire  _T_20 = _T_18 | _T_19; // @[Hello.scala 59:27]
  wire  _T_21 = ClkCntr == 8'h30; // @[Hello.scala 61:17]
  wire  _T_22 = _T_20 | _T_21; // @[Hello.scala 60:27]
  wire  _T_23 = ClkCntr == 8'h34; // @[Hello.scala 62:17]
  wire  _T_24 = _T_22 | _T_23; // @[Hello.scala 61:27]
  wire  _T_25 = ClkCntr == 8'h38; // @[Hello.scala 63:17]
  wire  _T_26 = _T_24 | _T_25; // @[Hello.scala 62:27]
  wire  _T_27 = ClkCntr == 8'h3c; // @[Hello.scala 64:17]
  wire  _T_28 = _T_26 | _T_27; // @[Hello.scala 63:27]
  wire  _T_29 = ClkCntr == 8'h40; // @[Hello.scala 65:17]
  wire  _T_30 = _T_28 | _T_29; // @[Hello.scala 64:27]
  wire  _T_31 = ClkCntr == 8'h44; // @[Hello.scala 66:17]
  wire  _T_32 = _T_30 | _T_31; // @[Hello.scala 65:27]
  wire  _T_33 = ClkCntr == 8'h48; // @[Hello.scala 67:17]
  wire  _T_34 = _T_32 | _T_33; // @[Hello.scala 66:27]
  wire  _GEN_0 = _T_34 ? ~MCLKTckr : MCLKTckr; // @[Hello.scala 67:27 70:20 37:30]
  wire  _T_37 = _T_13 | _T_29; // @[Hello.scala 75:26]
  wire  _GEN_1 = _T_37 ? ~BCLKTckr : BCLKTckr; // @[Hello.scala 76:27 78:20 35:30]
  wire [5:0] _T_45 = 6'h20 - 6'h1; // @[Hello.scala 137:64]
  wire [7:0] _GEN_42 = {{2'd0}, _T_45}; // @[Hello.scala 137:55]
  wire [7:0] _bDATA_T_3 = _GEN_42 - Bit_Counter; // @[Hello.scala 141:50]
  wire [23:0] _bDATA_T_4 = 24'h970097 >> _bDATA_T_3; // @[Hello.scala 141:35]
  wire  _GEN_4 = Bit_Counter == 8'h0 | Bit_Counter <= _GEN_42 ? _bDATA_T_4[0] : bDATA; // @[Hello.scala 137:71 141:19 38:30]
  wire [31:0] _GEN_5 = Bit_Counter == 8'h0 | Bit_Counter <= _GEN_42 ? 32'h970097 : DATA; // @[Hello.scala 137:71 142:19 39:30]
  wire [31:0] sw_msb_lsb_16_R = {io_sw, 16'h0}; // @[Hello.scala 148:41]
  wire [31:0] _GEN_44 = {{16'd0}, io_sw}; // @[Hello.scala 150:50]
  wire [31:0] sw_msb_lsb_32 = _GEN_44 + sw_msb_lsb_16_R; // @[Hello.scala 150:50]
  wire [31:0] _bDATA_T_10 = sw_msb_lsb_32 >> _bDATA_T_3; // @[Hello.scala 152:36]
  wire  _GEN_6 = io_sw == 16'h0 ? _GEN_4 : _bDATA_T_10[0]; // @[Hello.scala 135:30 152:19]
  wire [31:0] _GEN_7 = io_sw == 16'h0 ? _GEN_5 : {{16'd0}, io_sw}; // @[Hello.scala 135:30 153:19]
  wire [5:0] _T_48 = 6'h20 / 2'h2; // @[Hello.scala 157:38]
  wire [5:0] _T_50 = _T_48 - 6'h1; // @[Hello.scala 157:45]
  wire [7:0] _GEN_46 = {{2'd0}, _T_50}; // @[Hello.scala 157:27]
  wire  _GEN_8 = Bit_Counter >= _GEN_46 | LRClkr; // @[Hello.scala 157:53 158:18 36:30]
  wire  _T_58 = Bit_Counter == _GEN_42; // @[Hello.scala 160:69]
  wire  _GEN_9 = Bit_Counter < _GEN_46 | Bit_Counter == _GEN_42 ? 1'h0 : _GEN_8; // @[Hello.scala 160:89 161:18]
  wire [7:0] _Bit_Counter_T_1 = Bit_Counter + 8'h1; // @[Hello.scala 172:38]
  wire [7:0] _GEN_10 = _T_58 ? 8'h0 : _Bit_Counter_T_1; // @[Hello.scala 165:46 166:23 172:23]
  wire  _GEN_17 = current_state & _T_58; // @[Hello.scala 103:15 115:26]
  wire  _GEN_18 = ~current_state ? 1'h0 : current_state; // @[Hello.scala 115:26 119:21]
  wire  _GEN_19 = ~current_state ? 1'h0 : _GEN_17; // @[Hello.scala 115:26 120:21]
  wire  _GEN_20 = ~current_state ? 1'h0 : LRClkr; // @[Hello.scala 115:26 121:21 97:15]
  wire  _GEN_21 = ~current_state ? 1'h0 : BCLKTckr; // @[Hello.scala 115:26 122:21 95:15]
  wire  _GEN_22 = ~current_state ? 1'h0 : MCLKTckr; // @[Hello.scala 115:26 123:21 96:15]
  wire [31:0] _GEN_23 = ~current_state ? 32'h0 : DATA; // @[Hello.scala 115:26 124:21 99:15]
  wire [7:0] _GEN_25 = ~current_state ? 8'h0 : Bit_Counter; // @[Hello.scala 115:26 126:21 94:15]
  wire  _GEN_26 = ~current_state | current_state; // @[Hello.scala 115:26 127:23 31:30]
  wire  _GEN_30 = Tckr & _GEN_18; // @[Hello.scala 104:15 113:23]
  assign io_Ready = Tckr & _GEN_19; // @[Hello.scala 103:15 113:23]
  assign io_LRCLK = Tckr ? _GEN_20 : LRClkr; // @[Hello.scala 113:23 97:15]
  assign io_BCLK = Tckr ? _GEN_21 : BCLKTckr; // @[Hello.scala 113:23 95:15]
  assign io_MCLK = Tckr ? _GEN_22 : MCLKTckr; // @[Hello.scala 113:23 96:15]
  assign io_DATA = Tckr ? _GEN_23 : DATA; // @[Hello.scala 113:23 99:15]
  assign io_bDATA = bDATA; // @[Hello.scala 98:15]
  assign io_State_o = {{1'd0}, _GEN_30};
  assign io_BitCntr = Tckr ? _GEN_25 : Bit_Counter; // @[Hello.scala 113:23 94:15]
  assign io_tick = Tckr; // @[Hello.scala 101:15]
  assign io_CLKR = {{8'd0}, ClkCntr}; // @[Hello.scala 100:15]
  always @(posedge clock) begin
    if (reset) begin // @[Hello.scala 31:30]
      current_state <= 1'h0; // @[Hello.scala 31:30]
    end else if (Tckr) begin // @[Hello.scala 113:23]
      current_state <= _GEN_26;
    end
    if (reset) begin // @[Hello.scala 32:30]
      Bit_Counter <= 8'h0; // @[Hello.scala 32:30]
    end else if (Tckr) begin // @[Hello.scala 113:23]
      if (~current_state) begin // @[Hello.scala 115:26]
        Bit_Counter <= 8'h0; // @[Hello.scala 125:21]
      end else if (current_state) begin // @[Hello.scala 115:26]
        Bit_Counter <= _GEN_10;
      end
    end
    if (reset) begin // @[Hello.scala 33:30]
      ClkCntr <= 8'h0; // @[Hello.scala 33:30]
    end else if (_T_29) begin // @[Hello.scala 83:26]
      ClkCntr <= 8'h0; // @[Hello.scala 86:13]
    end else begin
      ClkCntr <= _ClkCntr_T_1; // @[Hello.scala 47:11]
    end
    if (reset) begin // @[Hello.scala 34:30]
      Tckr <= 1'h0; // @[Hello.scala 34:30]
    end else begin
      Tckr <= _T_29;
    end
    BCLKTckr <= reset | _GEN_1; // @[Hello.scala 35:{30,30}]
    if (reset) begin // @[Hello.scala 36:30]
      LRClkr <= 1'h0; // @[Hello.scala 36:30]
    end else if (Tckr) begin // @[Hello.scala 113:23]
      if (!(~current_state)) begin // @[Hello.scala 115:26]
        if (current_state) begin // @[Hello.scala 115:26]
          LRClkr <= _GEN_9;
        end
      end
    end
    MCLKTckr <= reset | _GEN_0; // @[Hello.scala 37:{30,30}]
    if (reset) begin // @[Hello.scala 38:30]
      bDATA <= 1'h0; // @[Hello.scala 38:30]
    end else if (Tckr) begin // @[Hello.scala 113:23]
      if (!(~current_state)) begin // @[Hello.scala 115:26]
        if (current_state) begin // @[Hello.scala 115:26]
          bDATA <= _GEN_6;
        end
      end
    end
    if (reset) begin // @[Hello.scala 39:30]
      DATA <= 32'h0; // @[Hello.scala 39:30]
    end else if (Tckr) begin // @[Hello.scala 113:23]
      if (!(~current_state)) begin // @[Hello.scala 115:26]
        if (current_state) begin // @[Hello.scala 115:26]
          DATA <= _GEN_7;
        end
      end
    end
  end
// Register and memory initialization
`ifdef RANDOMIZE_GARBAGE_ASSIGN
`define RANDOMIZE
`endif
`ifdef RANDOMIZE_INVALID_ASSIGN
`define RANDOMIZE
`endif
`ifdef RANDOMIZE_REG_INIT
`define RANDOMIZE
`endif
`ifdef RANDOMIZE_MEM_INIT
`define RANDOMIZE
`endif
`ifndef RANDOM
`define RANDOM $random
`endif
`ifdef RANDOMIZE_MEM_INIT
  integer initvar;
`endif
`ifndef SYNTHESIS
`ifdef FIRRTL_BEFORE_INITIAL
`FIRRTL_BEFORE_INITIAL
`endif
initial begin
  `ifdef RANDOMIZE
    `ifdef INIT_RANDOM
      `INIT_RANDOM
    `endif
    `ifndef VERILATOR
      `ifdef RANDOMIZE_DELAY
        #`RANDOMIZE_DELAY begin end
      `else
        #0.002 begin end
      `endif
    `endif
`ifdef RANDOMIZE_REG_INIT
  _RAND_0 = {1{`RANDOM}};
  current_state = _RAND_0[0:0];
  _RAND_1 = {1{`RANDOM}};
  Bit_Counter = _RAND_1[7:0];
  _RAND_2 = {1{`RANDOM}};
  ClkCntr = _RAND_2[7:0];
  _RAND_3 = {1{`RANDOM}};
  Tckr = _RAND_3[0:0];
  _RAND_4 = {1{`RANDOM}};
  BCLKTckr = _RAND_4[0:0];
  _RAND_5 = {1{`RANDOM}};
  LRClkr = _RAND_5[0:0];
  _RAND_6 = {1{`RANDOM}};
  MCLKTckr = _RAND_6[0:0];
  _RAND_7 = {1{`RANDOM}};
  bDATA = _RAND_7[0:0];
  _RAND_8 = {1{`RANDOM}};
  DATA = _RAND_8[31:0];
`endif // RANDOMIZE_REG_INIT
  `endif // RANDOMIZE
end // initial
`ifdef FIRRTL_AFTER_INITIAL
`FIRRTL_AFTER_INITIAL
`endif
`endif // SYNTHESIS
endmodule

test_run_dir/I2S_Transmitter_should_pass/I2S_Transmitter.vcd
$date
2022-09-14T20:04+0000
$end
$version
0.2
$end
$comment

$end
$timescale 1ns  $end
$scope module I2S_Transmitter $end
 $var wire 1 ! MCLKTckr $end
 $var wire 1 " io_BCLK $end
 $var wire 32 # sw_msb_lsb_16_R $end
 $var wire 32 $ io_DATA $end
 $var wire 8 % ClkCntr $end
 $var wire 32 & io_Tx $end
 $var wire 16 ' io_sw $end
 $var wire 1 ( io_bDATA $end
 $var wire 1 ) io_LRCLK $end
 $var wire 1 * io_MCLK $end
 $var wire 1 + Tckr $end
 $var wire 2 , io_State_o $end
 $var wire 1 - current_state $end
 $var wire 8 . io_BitCntr $end
 $var wire 16 / io_CLKR $end
 $var wire 8 0 Bit_Counter $end
 $var wire 1 1 io_tick $end
 $var wire 1 2 clock $end
 $var wire 1 3 LRClkr $end
 $var wire 1 4 BCLKTckr $end
 $var wire 1 5 io_Ready $end
 $var wire 1 6 bDATA $end
 $var wire 32 7 DATA $end
 $var wire 1 8 reset $end
 $var wire 32 9 sw_msb_lsb_32 $end
$upscope $end
$enddefinitions $end
$dumpvars
b00000000000000000000000000000000 &
04
05
0-
b00000000 0
06
b00000000000000000000000000000000 7
0!
0(
b0000000000000000 '
0"
01
b00000000000000000000000000000000 #
0)
08
b00000000000000000000000000000000 9
b0000000000000000 /
0*
b00000000 %
0+
b00000000000000000000000000000000 $
02
b00 ,
03
b00000000 .
$end
#0
18
#1
1!
14
1"
12
1*
#6
08
b00000000000001110000000000000000 #
02
b0000000000000111 '
b00000000000001110000000000000111 9
#11
b00000001 %
12
b0000000000000001 /
#16
02
#21
b00000010 %
12
b0000000000000010 /
#26
02
#31
b00000011 %
12
b0000000000000011 /
#36
02
#41
b00000100 %
12
b0000000000000100 /
#46
02
#51
0!
b00000101 %
12
0*
b0000000000000101 /
#56
02
#61
b00000110 %
12
b0000000000000110 /
#66
02
#71
b00000111 %
12
b0000000000000111 /
#76
02
#81
b00001000 %
12
b0000000000001000 /
#86
02
#91
1!
b00001001 %
12
1*
b0000000000001001 /
#96
02
#101
b00001010 %
12
b0000000000001010 /
#106
02
#111
b00001011 %
12
b0000000000001011 /
#116
02
#121
b00001100 %
12
b0000000000001100 /
#126
02
#131
0!
b00001101 %
12
0*
b0000000000001101 /
#136
02
#141
b00001110 %
12
b0000000000001110 /
#146
02
#151
b00001111 %
12
b0000000000001111 /
#156
02
#161
b00010000 %
12
b0000000000010000 /
#166
02
#171
1!
b00010001 %
12
1*
b0000000000010001 /
#176
02
#181
b00010010 %
12
b0000000000010010 /
#186
02
#191
b00010011 %
12
b0000000000010011 /
#196
02
#201
b00010100 %
12
b0000000000010100 /
#206
02
#211
0!
b00010101 %
12
0*
b0000000000010101 /
#216
02
#221
b00010110 %
12
b0000000000010110 /
#226
02
#231
b00010111 %
12
b0000000000010111 /
#236
02
#241
b00011000 %
12
b0000000000011000 /
#246
02
#251
1!
b00011001 %
12
1*
b0000000000011001 /
#256
02
#261
b00011010 %
12
b0000000000011010 /
#266
02
#271
b00011011 %
12
b0000000000011011 /
#276
02
#281
b00011100 %
12
b0000000000011100 /
#286
02
#291
0!
b00011101 %
12
0*
b0000000000011101 /
#296
02
#301
b00011110 %
12
b0000000000011110 /
#306
02
#311
b00011111 %
12
b0000000000011111 /
#316
02
#321
b00100000 %
12
b0000000000100000 /
#326
02
#331
1!
b00100001 %
04
0"
12
1*
b0000000000100001 /
#336
02
#341
b00100010 %
12
b0000000000100010 /
#346
02
#351
b00100011 %
12
b0000000000100011 /
#356
02
#361
b00100100 %
12
b0000000000100100 /
#366
02
#371
0!
b00100101 %
12
0*
b0000000000100101 /
#376
02
#381
b00100110 %
12
b0000000000100110 /
#386
02
#391
b00100111 %
12
b0000000000100111 /
#396
02
#401
b00101000 %
12
b0000000000101000 /
#406
02
#411
1!
b00101001 %
12
1*
b0000000000101001 /
#416
02
#421
b00101010 %
12
b0000000000101010 /
#426
02
#431
b00101011 %
12
b0000000000101011 /
#436
02
#441
b00101100 %
12
b0000000000101100 /
#446
02
#451
0!
b00101101 %
12
0*
b0000000000101101 /
#456
02
#461
b00101110 %
12
b0000000000101110 /
#466
02
#471
b00101111 %
12
b0000000000101111 /
#476
02
#481
b00110000 %
12
b0000000000110000 /
#486
02
#491
1!
b00110001 %
12
1*
b0000000000110001 /
#496
02
#501
b00110010 %
12
b0000000000110010 /
#506
02
#511
b00110011 %
12
b0000000000110011 /
#516
02
#521
b00110100 %
12
b0000000000110100 /
#526
02
#531
0!
b00110101 %
12
0*
b0000000000110101 /
#536
02
#541
b00110110 %
12
b0000000000110110 /
#546
02
#551
b00110111 %
12
b0000000000110111 /
#556
02
#561
b00111000 %
12
b0000000000111000 /
#566
02
#571
1!
b00111001 %
12
1*
b0000000000111001 /
#576
02
#581
b00111010 %
12
b0000000000111010 /
#586
02
#591
b00111011 %
12
b0000000000111011 /
#596
02
#601
b00111100 %
12
b0000000000111100 /
#606
02
#611
0!
b00111101 %
12
0*
b0000000000111101 /
#616
02
#621
b00111110 %
12
b0000000000111110 /
#626
02
#631
b00111111 %
12
b0000000000111111 /
#636
02
#641
b01000000 %
12
b0000000001000000 /
#646
02
#651
1!
b00000000 %
14
11
12
1+
b0000000000000000 /
#656
02
#661
1-
b00000001 %
1"
01
12
1*
0+
b0000000000000001 /
#666
02
#671
b00000010 %
12
b0000000000000010 /
#676
02
#681
b00000011 %
12
b0000000000000011 /
#686
02
#691
b00000100 %
12
b0000000000000100 /
#696
02
#701
0!
b00000101 %
12
0*
b0000000000000101 /
#706
02
#711
b00000110 %
12
b0000000000000110 /
#716
02
#721
b00000111 %
12
b0000000000000111 /
#726
02
#731
b00001000 %
12
b0000000000001000 /
#736
02
#741
1!
b00001001 %
12
1*
b0000000000001001 /
#746
02
#751
b00001010 %
12
b0000000000001010 /
#756
02
#761
b00001011 %
12
b0000000000001011 /
#766
02
#771
b00001100 %
12
b0000000000001100 /
#776
02
#781
0!
b00001101 %
12
0*
b0000000000001101 /
#786
02
#791
b00001110 %
12
b0000000000001110 /
#796
02
#801
b00001111 %
12
b0000000000001111 /
#806
02
#811
b00010000 %
12
b0000000000010000 /
#816
02
#821
1!
b00010001 %
12
1*
b0000000000010001 /
#826
02
#831
b00010010 %
12
b0000000000010010 /
#836
02
#841
b00010011 %
12
b0000000000010011 /
#846
02
#851
b00010100 %
12
b0000000000010100 /
#856
02
#861
0!
b00010101 %
12
0*
b0000000000010101 /
#866
02
#871
b00010110 %
12
b0000000000010110 /
#876
02
#881
b00010111 %
12
b0000000000010111 /
#886
02
#891
b00011000 %
12
b0000000000011000 /
#896
02
#901
1!
b00011001 %
12
1*
b0000000000011001 /
#906
02
#911
b00011010 %
12
b0000000000011010 /
#916
02
#921
b00011011 %
12
b0000000000011011 /
#926
02
#931
b00011100 %
12
b0000000000011100 /
#936
02
#941
0!
b00011101 %
12
0*
b0000000000011101 /
#946
02
#951
b00011110 %
12
b0000000000011110 /
#956
02
#961
b00011111 %
12
b0000000000011111 /
#966
02
#971
b00100000 %
12
b0000000000100000 /
#976
02
#981
1!
b00100001 %
04
0"
12
1*
b0000000000100001 /
#986
02
#991
b00100010 %
12
b0000000000100010 /
#996
02
#1001
b00100011 %
12
b0000000000100011 /
#1006
02
#1011
b00100100 %
12
b0000000000100100 /
#1016
02
#1021
0!
b00100101 %
12
0*
b0000000000100101 /
#1026
02
#1031
b00100110 %
12
b0000000000100110 /
#1036
02
#1041
b00100111 %
12
b0000000000100111 /
#1046
02
#1051
b00101000 %
12
b0000000000101000 /
#1056
02
#1061
1!
b00101001 %
12
1*
b0000000000101001 /
#1066
02
#1071
b00101010 %
12
b0000000000101010 /
#1076
02
#1081
b00101011 %
12
b0000000000101011 /
#1086
02
#1091
b00101100 %
12
b0000000000101100 /
#1096
02
#1101
0!
b00101101 %
12
0*
b0000000000101101 /
#1106
02
#1111
b00101110 %
12
b0000000000101110 /
#1116
02
#1121
b00101111 %
12
b0000000000101111 /
#1126
02
#1131
b00110000 %
12
b0000000000110000 /
#1136
02
#1141
1!
b00110001 %
12
1*
b0000000000110001 /
#1146
02
#1151
b00110010 %
12
b0000000000110010 /
#1156
02
#1161
b00110011 %
12
b0000000000110011 /
#1166
02
#1171
b00110100 %
12
b0000000000110100 /
#1176
02
#1181
0!
b00110101 %
12
0*
b0000000000110101 /
#1186
02
#1191
b00110110 %
12
b0000000000110110 /
#1196
02
#1201
b00110111 %
12
b0000000000110111 /
#1206
02
#1211
b00111000 %
12
b0000000000111000 /
#1216
02
#1221
1!
b00111001 %
12
1*
b0000000000111001 /
#1226
02
#1231
b00111010 %
12
b0000000000111010 /
#1236
02
#1241
b00111011 %
12
b0000000000111011 /
#1246
02
#1251
b00111100 %
12
b0000000000111100 /
#1256
02
#1261
0!
b00111101 %
12
0*
b0000000000111101 /
#1266
02
#1271
b00111110 %
12
b0000000000111110 /
#1276
02
#1281
b00111111 %
12
b0000000000111111 /
#1286
02
#1291
b01000000 %
12
b0000000001000000 /
#1296
02
#1301
1!
b00000000 %
14
11
1"
12
1*
1+
b0000000000000000 /
b01 ,
#1306
02
#1311
b00000001 0
b00000001 %
01
b00000001 .
12
b00000000000000000000000000000111 $
0+
b00000000000000000000000000000111 7
b0000000000000001 /
b00 ,
#1316
02
#1321
b00000010 %
12
b0000000000000010 /
#1326
02
#1331
b00000011 %
12
b0000000000000011 /
#1336
02
#1341
b00000100 %
12
b0000000000000100 /
#1346
02
#1351
0!
b00000101 %
12
0*
b0000000000000101 /
#1356
02
#1361
b00000110 %
12
b0000000000000110 /
#1366
02
#1371
b00000111 %
12
b0000000000000111 /
#1376
02
#1381
b00001000 %
12
b0000000000001000 /
#1386
02
#1391
1!
b00001001 %
12
1*
b0000000000001001 /
#1396
02
#1401
b00001010 %
12
b0000000000001010 /
#1406
02
#1411
b00001011 %
12
b0000000000001011 /
#1416
02
#1421
b00001100 %
12
b0000000000001100 /
#1426
02
#1431
0!
b00001101 %
12
0*
b0000000000001101 /
#1436
02
#1441
b00001110 %
12
b0000000000001110 /
#1446
02
#1451
b00001111 %
12
b0000000000001111 /
#1456
02
#1461
b00010000 %
12
b0000000000010000 /
#1466
02
#1471
1!
b00010001 %
12
1*
b0000000000010001 /
#1476
02
#1481
b00010010 %
12
b0000000000010010 /
#1486
02
#1491
b00010011 %
12
b0000000000010011 /
#1496
02
#1501
b00010100 %
12
b0000000000010100 /
#1506
02
#1511
0!
b00010101 %
12
0*
b0000000000010101 /
#1516
02
#1521
b00010110 %
12
b0000000000010110 /
#1526
02
#1531
b00010111 %
12
b0000000000010111 /
#1536
02
#1541
b00011000 %
12
b0000000000011000 /
#1546
02
#1551
1!
b00011001 %
12
1*
b0000000000011001 /
#1556
02
#1561
b00011010 %
12
b0000000000011010 /
#1566
02
#1571
b00011011 %
12
b0000000000011011 /
#1576
02
#1581
b00011100 %
12
b0000000000011100 /
#1586
02
#1591
0!
b00011101 %
12
0*
b0000000000011101 /
#1596
02
#1601
b00011110 %
12
b0000000000011110 /
#1606
02
#1611
b00011111 %
12
b0000000000011111 /
#1616
02
#1621
b00100000 %
12
b0000000000100000 /
#1626
02
#1631
1!
b00100001 %
04
0"
12
1*
b0000000000100001 /
#1636
02
#1641
b00100010 %
12
b0000000000100010 /
#1646
02
#1651
b00100011 %
12
b0000000000100011 /
#1656
02
#1661
b00100100 %
12
b0000000000100100 /
#1666
02
#1671
0!
b00100101 %
12
0*
b0000000000100101 /
#1676
02
#1681
b00100110 %
12
b0000000000100110 /
#1686
02
#1691
b00100111 %
12
b0000000000100111 /
#1696
02
#1701
b00101000 %
12
b0000000000101000 /
#1706
02
#1711
1!
b00101001 %
12
1*
b0000000000101001 /
#1716
02
#1721
b00101010 %
12
b0000000000101010 /
#1726
02
#1731
b00101011 %
12
b0000000000101011 /
#1736
02
#1741
b00101100 %
12
b0000000000101100 /
#1746
02
#1751
0!
b00101101 %
12
0*
b0000000000101101 /
#1756
02
#1761
b00101110 %
12
b0000000000101110 /
#1766
02
#1771
b00101111 %
12
b0000000000101111 /
#1776
02
#1781
b00110000 %
12
b0000000000110000 /
#1786
02
#1791
1!
b00110001 %
12
1*
b0000000000110001 /
#1796
02
#1801
b00110010 %
12
b0000000000110010 /
#1806
02
#1811
b00110011 %
12
b0000000000110011 /
#1816
02
#1821
b00110100 %
12
b0000000000110100 /
#1826
02
#1831
0!
b00110101 %
12
0*
b0000000000110101 /
#1836
02
#1841
b00110110 %
12
b0000000000110110 /
#1846
02
#1851
b00110111 %
12
b0000000000110111 /
#1856
02
#1861
b00111000 %
12
b0000000000111000 /
#1866
02
#1871
1!
b00111001 %
12
1*
b0000000000111001 /
#1876
02
#1881
b00111010 %
12
b0000000000111010 /
#1886
02
#1891
b00111011 %
12
b0000000000111011 /
#1896
02
#1901
b00111100 %
12
b0000000000111100 /
#1906
02
#1911
0!
b00111101 %
12
0*
b0000000000111101 /
#1916
02
#1921
b00111110 %
12
b0000000000111110 /
#1926
02
#1931
b00111111 %
12
b0000000000111111 /
#1936
02
#1941
b01000000 %
12
b0000000001000000 /
#1946
02
#1951
1!
b00000000 %
14
11
1"
12
1*
1+
b0000000000000000 /
b01 ,
#1956
02
#1961
b00000010 0
b00000001 %
01
b00000010 .
12
0+
b0000000000000001 /
b00 ,
#1966
02
#1971
b00000010 %
12
b0000000000000010 /
#1976
02
#1981
b00000011 %
12
b0000000000000011 /
#1986
02
#1991
b00000100 %
12
b0000000000000100 /
#1996
02
#2001
0!
b00000101 %
12
0*
b0000000000000101 /
#2006
02
#2011
b00000110 %
12
b0000000000000110 /
#2016
02
#2021
b00000111 %
12
b0000000000000111 /
#2026
02
#2031
b00001000 %
12
b0000000000001000 /
#2036
02
#2041
1!
b00001001 %
12
1*
b0000000000001001 /
#2046
02
#2051
b00001010 %
12
b0000000000001010 /
#2056
02
#2061
b00001011 %
12
b0000000000001011 /
#2066
02
#2071
b00001100 %
12
b0000000000001100 /
#2076
02
#2081
0!
b00001101 %
12
0*
b0000000000001101 /
#2086
02
#2091
b00001110 %
12
b0000000000001110 /
#2096
02
#2101
b00001111 %
12
b0000000000001111 /
#2106
02
#2111
b00010000 %
12
b0000000000010000 /
#2116
02
#2121
1!
b00010001 %
12
1*
b0000000000010001 /
#2126
02
#2131
b00010010 %
12
b0000000000010010 /
#2136
02
#2141
b00010011 %
12
b0000000000010011 /
#2146
02
#2151
b00010100 %
12
b0000000000010100 /
#2156
02
#2161
0!
b00010101 %
12
0*
b0000000000010101 /
#2166
02
#2171
b00010110 %
12
b0000000000010110 /
#2176
02
#2181
b00010111 %
12
b0000000000010111 /
#2186
02
#2191
b00011000 %
12
b0000000000011000 /
#2196
02
#2201
1!
b00011001 %
12
1*
b0000000000011001 /
#2206
02
#2211
b00011010 %
12
b0000000000011010 /
#2216
02
#2221
b00011011 %
12
b0000000000011011 /
#2226
02
#2231
b00011100 %
12
b0000000000011100 /
#2236
02
#2241
0!
b00011101 %
12
0*
b0000000000011101 /
#2246
02
#2251
b00011110 %
12
b0000000000011110 /
#2256
02
#2261
b00011111 %
12
b0000000000011111 /
#2266
02
#2271
b00100000 %
12
b0000000000100000 /
#2276
02
#2281
1!
b00100001 %
04
0"
12
1*
b0000000000100001 /
#2286
02
#2291
b00100010 %
12
b0000000000100010 /
#2296
02
#2301
b00100011 %
12
b0000000000100011 /
#2306
02
#2311
b00100100 %
12
b0000000000100100 /
#2316
02
#2321
0!
b00100101 %
12
0*
b0000000000100101 /
#2326
02
#2331
b00100110 %
12
b0000000000100110 /
#2336
02
#2341
b00100111 %
12
b0000000000100111 /
#2346
02
#2351
b00101000 %
12
b0000000000101000 /
#2356
02
#2361
1!
b00101001 %
12
1*
b0000000000101001 /
#2366
02
#2371
b00101010 %
12
b0000000000101010 /
#2376
02
#2381
b00101011 %
12
b0000000000101011 /
#2386
02
#2391
b00101100 %
12
b0000000000101100 /
#2396
02
#2401
0!
b00101101 %
12
0*
b0000000000101101 /
#2406
02
#2411
b00101110 %
12
b0000000000101110 /
#2416
02
#2421
b00101111 %
12
b0000000000101111 /
#2426
02
#2431
b00110000 %
12
b0000000000110000 /
#2436
02
#2441
1!
b00110001 %
12
1*
b0000000000110001 /
#2446
02
#2451
b00110010 %
12
b0000000000110010 /
#2456
02
#2461
b00110011 %
12
b0000000000110011 /
#2466
02
#2471
b00110100 %
12
b0000000000110100 /
#2476
02
#2481
0!
b00110101 %
12
0*
b0000000000110101 /
#2486
02
#2491
b00110110 %
12
b0000000000110110 /
#2496
02
#2501
b00110111 %
12
b0000000000110111 /
#2506
02
#2511
b00111000 %
12
b0000000000111000 /
#2516
02
#2521
1!
b00111001 %
12
1*
b0000000000111001 /
#2526
02
#2531
b00111010 %
12
b0000000000111010 /
#2536
02
#2541
b00111011 %
12
b0000000000111011 /
#2546
02
#2551
b00111100 %
12
b0000000000111100 /
#2556
02
#2561
0!
b00111101 %
12
0*
b0000000000111101 /
#2566
02
#2571
b00111110 %
12
b0000000000111110 /
#2576
02
#2581
b00111111 %
12
b0000000000111111 /
#2586
02
#2591
b01000000 %
12
b0000000001000000 /
#2596
02
#2601
1!
b00000000 %
14
11
1"
12
1*
1+
b0000000000000000 /
b01 ,
#2606
02
#2611
b00000011 0
b00000001 %
01
b00000011 .
12
0+
b0000000000000001 /
b00 ,
#2616
02
#2621
b00000010 %
12
b0000000000000010 /
#2626
02
#2631
b00000011 %
12
b0000000000000011 /
#2636
02
#2641
b00000100 %
12
b0000000000000100 /
#2646
02
#2651
0!
b00000101 %
12
0*
b0000000000000101 /
#2656
02
